flake8_adjustable_complexity/__init__.py
flake8_adjustable_complexity/ast_helpers.py
flake8_adjustable_complexity/checker.py
flake8_adjustable_complexity/complexity_helpers.py
flake8_adjustable_complexity/config.py
flake8_adjustable_complexity/list_helpers.py
flake8_adjustable_complexity/violations.py
flake8_adjustable_complexity-0.0.6.dist-info/LICENSE
flake8_adjustable_complexity-0.0.6.dist-info/METADATA
flake8_adjustable_complexity-0.0.6.dist-info/WHEEL
flake8_adjustable_complexity-0.0.6.dist-info/entry_points.txt
flake8_adjustable_complexity-0.0.6.dist-info/top_level.txt
flake8_adjustable_complexity-0.0.6.dist-info/RECORD
