Metadata-Version: 2.1
Name: flake8-adjustable-complexity
Version: 0.0.6
Summary: A flake8 extension that checks cyclomatic complexity and calculates max complexity limit in runtime
Home-page: https://github.com/best-doctor/flake8-adjustable-complexity
Author: Ilya Lebedev
Author-email: melevir@gmail.com
License: MIT
Keywords: flake8 annotations
Platform: UNKNOWN
Classifier: Framework :: Pytest
Classifier: Topic :: Software Development :: Testing
Classifier: Programming Language :: Python
Classifier: Programming Language :: Python :: 3.7
Classifier: Programming Language :: Python :: 3.8
Classifier: Programming Language :: Python :: 3.9
Classifier: Programming Language :: Python :: 3.10
Requires-Python: >=3.7
License-File: LICENSE
Requires-Dist: flake8
